tenex/__init__.py
tenex/dtype/__init__.py
tenex/shape/__init__.py
tenex/shape/broadcast.py
tenex/shape/matmul.py
tenex/shape/stack.py
tenex/tensor/__init__.py
tenex/tensor/arange.py
tenex/tensor/dtype/__init__.py
tenex/tensor/shape/__init__.py
tenex/tensor/shape/broadcast.py
tenex/tensor/shape/matmul.py
tenex/tensor/shape/stack.py
tenex-0.1.0.dist-info/licenses/LICENSE
tenex-0.1.0.dist-info/METADATA
tenex-0.1.0.dist-info/WHEEL
tenex-0.1.0.dist-info/top_level.txt
tenex-0.1.0.dist-info/RECORD
