Metadata-Version: 2.4
Name: tenex
Version: 0.1.0
Summary: The better way to handle ndarray and train model.
Home-page: https://github.com/lihz6/tenex
Author: tenex
Author-email: lihongzhang@bytedance.com
Classifier: Programming Language :: Python :: 3.7
Classifier: Programming Language :: Python :: 3 :: Only
Classifier: License :: OSI Approved :: MIT License
Classifier: Operating System :: OS Independent
Requires-Python: >=3.7
License-File: LICENSE
Dynamic: author
Dynamic: author-email
Dynamic: classifier
Dynamic: description
Dynamic: description-content-type
Dynamic: home-page
Dynamic: license-file
Dynamic: requires-python
Dynamic: summary
